fastml_contest/__init__.py
fastml_contest/cat_num_detect.py
fastml_contest/catboost_focal_loss.py
fastml_contest/fast_catboost.py
fastml_contest/fast_flaml.py
fastml_contest/fast_lgbm.py
fastml_contest/fast_xgb.py
fastml_contest/feature_en.py
fastml_contest/ff_all1.py
fastml_contest/ff_all2.py
fastml_contest/kmens_fe.py
fastml_contest/my_metrics.py
fastml_contest/printer.py
fastml_contest/target_xgboost.py
fastml_contets-0.7.0.dist-info/LICENSE
fastml_contets-0.7.0.dist-info/METADATA
fastml_contets-0.7.0.dist-info/WHEEL
fastml_contets-0.7.0.dist-info/top_level.txt
fastml_contets-0.7.0.dist-info/RECORD
