Metadata-Version: 2.1
Name: fastml_contets
Version: 0.7.0
Home-page: https://github.com/你的用户名/fastml_contest
Author: xuxy
Author-email: 
Classifier: Programming Language :: Python :: 3
Classifier: License :: OSI Approved :: MIT License
Classifier: Operating System :: OS Independent
Requires-Python: >=3.6
License-File: LICENSE
Requires-Dist: numpy
Requires-Dist: pandas
Requires-Dist: scikit-learn
